{"cameraMode":{"drawMode":0,"name":"Shaded","section":"Shading Mode"},"sceneLighting":true,"audioPlay":false,"sceneViewState":{"m_AlwaysRefresh":false,"showFog":true,"showSkybox":true,"showFlares":true,"showImageEffects":true,"showParticleSystems":true,"showVisualEffectGraphs":true,"m_FxEnabled":true},"in2DMode":false,"pivot":{"x":30.76276206970215,"y":-877.4775390625,"z":410.9864501953125},"rotation":{"x":0.5261667966842651,"y":-0.014000538736581803,"z":0.009315441362559796,"w":0.8509315252304077},"size":545.32080078125,"orthographic":false}